odoo/addons/fleet_vehicle_inspection_template/README.rst
odoo/addons/fleet_vehicle_inspection_template/__init__.py
odoo/addons/fleet_vehicle_inspection_template/__manifest__.py
odoo/addons/fleet_vehicle_inspection_template/demo/fleet_vehicle_inspection_template.xml
odoo/addons/fleet_vehicle_inspection_template/i18n/fleet_vehicle_inspection_template.pot
odoo/addons/fleet_vehicle_inspection_template/i18n/it.po
odoo/addons/fleet_vehicle_inspection_template/i18n/pt_BR.po
odoo/addons/fleet_vehicle_inspection_template/models/__init__.py
odoo/addons/fleet_vehicle_inspection_template/models/fleet_vehicle_inspection.py
odoo/addons/fleet_vehicle_inspection_template/models/fleet_vehicle_inspection_template.py
odoo/addons/fleet_vehicle_inspection_template/models/fleet_vehicle_inspection_template_line.py
odoo/addons/fleet_vehicle_inspection_template/readme/CONFIGURE.rst
odoo/addons/fleet_vehicle_inspection_template/readme/CONTRIBUTORS.rst
odoo/addons/fleet_vehicle_inspection_template/readme/CREDITS.rst
odoo/addons/fleet_vehicle_inspection_template/readme/DESCRIPTION.rst
odoo/addons/fleet_vehicle_inspection_template/readme/ROADMAP.rst
odoo/addons/fleet_vehicle_inspection_template/security/fleet_vehicle_inspection_template.xml
odoo/addons/fleet_vehicle_inspection_template/security/fleet_vehicle_inspection_template_line.xml
odoo/addons/fleet_vehicle_inspection_template/static/description/banner.png
odoo/addons/fleet_vehicle_inspection_template/static/description/icon.png
odoo/addons/fleet_vehicle_inspection_template/static/description/index.html
odoo/addons/fleet_vehicle_inspection_template/tests/__init__.py
odoo/addons/fleet_vehicle_inspection_template/tests/test_fleet_vehicle_inspection_template.py
odoo/addons/fleet_vehicle_inspection_template/views/fleet_vehicle_inspection.xml
odoo/addons/fleet_vehicle_inspection_template/views/fleet_vehicle_inspection_template.xml
odoo/addons/fleet_vehicle_inspection_template/views/fleet_vehicle_inspection_template_line.xml
odoo14_addon_fleet_vehicle_inspection_template-14.0.1.0.1.dist-info/METADATA
odoo14_addon_fleet_vehicle_inspection_template-14.0.1.0.1.dist-info/WHEEL
odoo14_addon_fleet_vehicle_inspection_template-14.0.1.0.1.dist-info/top_level.txt
odoo14_addon_fleet_vehicle_inspection_template-14.0.1.0.1.dist-info/RECORD
